{"nodes":[{"id":"W7","label":"W7","data":{"dships":0,"backgroundColor":"rgba(255,164, 43,1)","fleets":[{"x":70,"y":0,"backgroundColor":"rgba(255,164, 43,1)","label":"F87=10","fontColor":"rgba( 0, 0, 0, 1)"}],"fontColor":"rgba( 0, 0, 0, 1)"}},{"id":"W23","label":"W23","data":{"dships":2,"backgroundColor":"rgba(255,164, 43,1)","fleets":[{"x":70,"y":0,"backgroundColor":"rgba(230,156, 58,1)","label":"F66=5","fontColor":"rgba( 0, 0, 0, 1)"},{"x":49.49747468305833,"y":49.49747468305832,"backgroundColor":"rgba(255,164, 43,1)","label":"F71=1","fontColor":"rgba( 0, 0, 0, 1)"}],"fontColor":"rgba( 0, 0, 0, 1)"}},{"id":"W61","label":"W61","data":{"dships":1,"backgroundColor":"rgba(255,164, 43,1)","fleets":[{"x":70,"y":0,"backgroundColor":"rgba(255,164, 43,1)","label":"F92=2","fontColor":"rgba( 0, 0, 0, 1)"},{"x":49.49747468305833,"y":49.49747468305832,"backgroundColor":"rgba(255,164, 43,1)","label":"F100=3","fontColor":"rgba( 0, 0, 0, 1)"},{"x":4.2862637970157365e-15,"y":70,"backgroundColor":"rgba(255,164, 43,1)","label":"F99=7","fontColor":"rgba( 0, 0, 0, 1)"},{"x":-49.49747468305832,"y":49.49747468305833,"backgroundColor":"rgba(255,164, 43,1)","label":"F125=1","fontColor":"rgba( 0, 0, 0, 1)"},{"x":-70,"y":8.572527594031473e-15,"backgroundColor":"rgba(255,164, 43,1)","label":"F77=4","fontColor":"rgba( 0, 0, 0, 1)"},{"x":-49.497474683058336,"y":-49.49747468305832,"backgroundColor":"rgba(255,164, 43,1)","label":"F138=4","fontColor":"rgba( 0, 0, 0, 1)"}],"fontColor":"rgba( 0, 0, 0, 1)"}},{"id":"W88","label":"W88","data":{"dships":1,"backgroundColor":"rgba(255,164, 43,1)","fleets":[{"x":70,"y":0,"backgroundColor":"rgba(255,164, 43,1)","label":"F145=1","fontColor":"rgba( 0, 0, 0, 1)"}],"fontColor":"rgba( 0, 0, 0, 1)"}},{"id":"W110","label":"W110","data":{"dships":5,"backgroundColor":"rgba( 32, 54, 71,1)","fleets":[{"x":70,"y":0,"backgroundColor":"rgba(255,164, 43,1)","label":"F76=1","fontColor":"rgba( 0, 0, 0, 1)"},{"x":49.49747468305833,"y":49.49747468305832,"backgroundColor":"rgba(255,164, 43,1)","label":"F38=18","fontColor":"rgba( 0, 0, 0, 1)"}],"fontColor":"rgba( 255, 255, 255, 1)"}},{"id":"W139","label":"W139","data":{"dships":1,"backgroundColor":"rgba(255,164, 43,1)","fleets":[{"x":70,"y":0,"backgroundColor":"rgba(230,156, 58,1)","label":"F13=5","fontColor":"rgba( 0, 0, 0, 1)"},{"x":49.49747468305833,"y":49.49747468305832,"backgroundColor":"rgba(255,164, 43,1)","label":"F51=1","fontColor":"rgba( 0, 0, 0, 1)"}],"fontColor":"rgba( 0, 0, 0, 1)"}},{"id":"W87","label":"W87","data":{"backgroundColor":"whitesmoke"}},{"id":"W29","label":"W29","data":{"backgroundColor":"whitesmoke"}},{"id":"W35","label":"W35","data":{"backgroundColor":"whitesmoke"}},{"id":"W122","label":"W122","data":{"backgroundColor":"whitesmoke"}},{"id":"W25","label":"W25","data":{"backgroundColor":"whitesmoke"}},{"id":"W120","label":"W120","data":{"backgroundColor":"whitesmoke"}}],"links":[{"id":"W7W88","source":"W7","target":"W88","label":"W7->W88"},{"id":"W7W110","source":"W7","target":"W110","label":"W7->W110"},{"id":"W23W88","source":"W23","target":"W88","label":"W23->W88"},{"id":"W23W139","source":"W23","target":"W139","label":"W23->W139"},{"id":"W61W87","source":"W61","target":"W87","label":"W61->W87"},{"id":"W61W88","source":"W61","target":"W88","label":"W61->W88"},{"id":"W29W61","source":"W61","target":"W29","label":"W61->W29"},{"id":"W61W88","source":"W88","target":"W61","label":"W88->W61"},{"id":"W7W88","source":"W88","target":"W7","label":"W88->W7"},{"id":"W23W88","source":"W88","target":"W23","label":"W88->W23"},{"id":"W35W110","source":"W110","target":"W35","label":"W110->W35"},{"id":"W110W122","source":"W110","target":"W122","label":"W110->W122"},{"id":"W7W110","source":"W110","target":"W7","label":"W110->W7"},{"id":"W23W139","source":"W139","target":"W23","label":"W139->W23"},{"id":"W25W139","source":"W139","target":"W25","label":"W139->W25"},{"id":"W120W139","source":"W139","target":"W120","label":"W139->W120"}]}